seloger_google_sheets/__init__.py
seloger_google_sheets/google_spreadsheets_service.py
seloger_google_sheets/real_estate.py
seloger_google_sheets/real_estate_filter.py
seloger_google_sheets/real_estate_service.py
seloger_google_sheets/real_estate_type.py
seloger_google_sheets/search_query.py
seloger_google_sheets/seloger_search_query.py
seloger_google_sheets/seloger_service.py
seloger_google_sheets/settings.py
seloger_google_sheets/spreadsheet_service.py
seloger_google_sheets/transaction_type.py
seloger_google_sheets-1.0.6.dist-info/METADATA
seloger_google_sheets-1.0.6.dist-info/WHEEL
seloger_google_sheets-1.0.6.dist-info/top_level.txt
seloger_google_sheets-1.0.6.dist-info/RECORD
