Metadata-Version: 2.1
Name: seloger-google-sheets
Version: 1.0.6
Summary: Tired of searching with your mouse ? Let's automate the process.
Home-page: https://github.com/arthuRHD/seloger-google-sheets
Author: Arthur RICHARD
Author-email: arthur.richard@protonmail.com
License: UNKNOWN
Platform: UNKNOWN
Classifier: Programming Language :: Python :: 3
Classifier: License :: OSI Approved :: MIT License
Classifier: Operating System :: OS Independent
Requires-Python: >=3.8
Requires-Dist: google-api-core (==2.8.2)
Requires-Dist: google-api-python-client (==2.52.0)
Requires-Dist: google-auth-httplib2 (==0.1.0)
Requires-Dist: google-auth-oauthlib (==0.5.2)
Requires-Dist: google-auth (==2.9.0)
Requires-Dist: pydantic (==1.9.1)
Requires-Dist: requests (==2.22.0)
